netbox_plugin_azuread/VERSION
netbox_plugin_azuread/__init__.py
netbox_plugin_azuread/backends.py
netbox_plugin_azuread/urls.py
netbox_plugin_azuread/views.py
netbox_plugin_azuread/templates/azure/login.html
netbox_plugin_azuread/templates/azure/login_2.x.html
netbox_plugin_azuread-1.2.0.dist-info/METADATA
netbox_plugin_azuread-1.2.0.dist-info/WHEEL
netbox_plugin_azuread-1.2.0.dist-info/top_level.txt
netbox_plugin_azuread-1.2.0.dist-info/RECORD
