Metadata-Version: 2.1
Name: netbox-plugin-azuread
Version: 1.2.0
Summary: Authenticate with Netbox via AzureAD
Home-page: https://github.com/marcus-crane/netbox-plugin-azuread
Author: Marcus Crane
License: MIT
Project-URL: Bug Tracker, https://github.com/marcus-crane/netbox-plugin-azuread/issues
Platform: UNKNOWN
Classifier: Development Status :: 5 - Production/Stable
Classifier: Environment :: Plugins
Classifier: Framework :: Django :: 3.2
Classifier: Intended Audience :: Developers
Classifier: Intended Audience :: System Administrators
Classifier: License :: OSI Approved :: MIT License
Classifier: Natural Language :: English
Classifier: Operating System :: OS Independent
Classifier: Programming Language :: Python :: 3 :: Only
Classifier: Topic :: Internet
Classifier: Topic :: Internet :: Name Service (DNS)
Classifier: Topic :: Internet :: WWW/HTTP :: HTTP Servers
Classifier: Topic :: Internet :: WWW/HTTP :: Site Management
Classifier: Topic :: System :: Networking
Classifier: Topic :: System :: Systems Administration :: Authentication/Directory
Requires-Python: >=3.6
